stone/__init__.py
stone/backend.py
stone/cli.py
stone/cli_helpers.py
stone/compiler.py
stone/py.typed
stone/typing_hacks.py
stone/backends/__init__.py
stone/backends/helpers.py
stone/backends/js_client.py
stone/backends/js_helpers.py
stone/backends/js_types.py
stone/backends/obj_c.py
stone/backends/obj_c_client.py
stone/backends/obj_c_helpers.py
stone/backends/obj_c_types.py
stone/backends/python_client.py
stone/backends/python_helpers.py
stone/backends/python_type_mapping.py
stone/backends/python_type_stubs.py
stone/backends/python_types.py
stone/backends/swift.py
stone/backends/swift_client.py
stone/backends/swift_helpers.py
stone/backends/swift_types.py
stone/backends/tsd_client.py
stone/backends/tsd_helpers.py
stone/backends/tsd_types.py
stone/backends/python_rsrc/__init__.py
stone/backends/python_rsrc/stone_base.py
stone/backends/python_rsrc/stone_serializers.py
stone/backends/python_rsrc/stone_validators.py
stone/frontend/__init__.py
stone/frontend/ast.py
stone/frontend/exception.py
stone/frontend/frontend.py
stone/frontend/ir_generator.py
stone/frontend/lexer.py
stone/frontend/parser.py
stone/ir/__init__.py
stone/ir/api.py
stone/ir/data_types.py
stone-3.3.8.dist-info/LICENSE
stone-3.3.8.dist-info/METADATA
stone-3.3.8.dist-info/WHEEL
stone-3.3.8.dist-info/entry_points.txt
stone-3.3.8.dist-info/top_level.txt
stone-3.3.8.dist-info/RECORD
