Metadata-Version: 2.1
Name: stone
Version: 3.3.8
Summary: Stone is an interface description language (IDL) for APIs.
Home-page: https://github.com/dropbox/stone
Author: Ken Elkabany
Author-email: kelkabany@dropbox.com
Maintainer: Dropbox
Maintainer-email: api-platform@dropbox.com
License: MIT License
Classifier: Development Status :: 5 - Production/Stable
Classifier: Intended Audience :: Developers
Classifier: License :: OSI Approved :: MIT License
Classifier: Operating System :: OS Independent
Classifier: Programming Language :: Python :: 3.5
Classifier: Programming Language :: Python :: 3.6
Classifier: Programming Language :: Python :: 3.7
Classifier: Topic :: Software Development :: Code Generators
Classifier: Topic :: Software Development :: Libraries :: Python Modules
License-File: LICENSE
Requires-Dist: ply>=3.4
Requires-Dist: six>=1.12.0
Requires-Dist: packaging>=21.0
